<annotation>
    <folder>dataset</folder>
    <filename>120.jpg</filename>
    <path>/home/zhaocake/文档/projects/projects/python_projects/mmdetection/make_dataset/dataset/120.jpg</path>
    <source>
        <database>Unknown</database>
    </source>
    <size>
        <width>1920</width>
        <height>1080</height>
        <depth>3</depth>
    </size>
    <segmented>0</segmented>
    <object>
        <name>circle</name>
        <pose>Unspecified</pose>
        <truncated>0</truncated>
        <difficult>0</difficult>
        <bndbox>
            <xmin>760</xmin>
            <ymin>548</ymin>
            <xmax>1181</xmax>
            <ymax>1014</ymax>
        </bndbox>
    </object>
</annotation>
